{
  "sections": {
    "aw-hero": {
      "type": "image-banner",
      "blocks": {
        "aw-hero-heading": {
          "type": "heading",
          "settings": {
            "heading": "AltinWorld — Tijdloze sieraden met karakter",
            "heading_size": "h0"
          }
        },
        "aw-hero-text": {
          "type": "text",
          "settings": {
            "text": "Ontdek onze collectie handgeselecteerde sieraden voor elk bijzonder moment.",
            "text_style": "subtitle"
          }
        },
        "aw-hero-button": {
          "type": "buttons",
          "settings": {
            "button_label_1": "Shop nu",
            "button_link_1": "shopify://collections/all",
            "button_style_secondary_1": false,
            "button_label_2": "Bekijk collecties",
            "button_link_2": "shopify://collections",
            "button_style_secondary_2": true
          }
        }
      },
      "block_order": [
        "aw-hero-heading",
        "aw-hero-text",
        "aw-hero-button"
      ],
      "settings": {
        "image_overlay_opacity": 35,
        "image_height": "large",
        "desktop_content_position": "middle-left",
        "show_text_box": false,
        "desktop_content_alignment": "left",
        "color_scheme": "scheme-3",
        "mobile_content_alignment": "center",
        "stack_images_on_mobile": false,
        "show_text_below": false,
        "padding_top": 0,
        "padding_bottom": 0
      }
    },
    "aw-collectie": {
      "type": "featured-collection",
      "settings": {
        "title": "Onze collectie",
        "heading_size": "h2",
        "description": "",
        "show_description": false,
        "description_style": "body",
        "collection": "all",
        "products_to_show": 8,
        "columns_desktop": 4,
        "full_width": false,
        "show_view_all": true,
        "view_all_style": "solid",
        "enable_desktop_slider": false,
        "color_scheme": "scheme-2",
        "image_ratio": "portrait",
        "image_shape": "default",
        "show_secondary_image": true,
        "show_vendor": false,
        "show_rating": false,
        "quick_add": "standard",
        "columns_mobile": "2",
        "swipe_on_mobile": false,
        "padding_top": 56,
        "padding_bottom": 56
      }
    },
    "aw-usp": {
      "type": "multicolumn",
      "blocks": {
        "aw-usp-1": {
          "type": "column",
          "settings": {
            "title": "Gratis verzending",
            "text": "<p>Gratis verzending bij bestellingen vanaf €75. Snel en zorgvuldig verpakt aan huis bezorgd.<\/p>",
            "link_label": "",
            "link": ""
          }
        },
        "aw-usp-2": {
          "type": "column",
          "settings": {
            "title": "30 dagen retour",
            "text": "<p>Niet tevreden? Retourneer uw aankoop binnen 30 dagen — zonder vragen, zonder gedoe.<\/p>",
            "link_label": "",
            "link": ""
          }
        },
        "aw-usp-3": {
          "type": "column",
          "settings": {
            "title": "Veilig betalen",
            "text": "<p>Betaal veilig via iDEAL, creditcard of PayPal. Uw gegevens zijn altijd beschermd.<\/p>",
            "link_label": "",
            "link": ""
          }
        }
      },
      "block_order": [
        "aw-usp-1",
        "aw-usp-2",
        "aw-usp-3"
      ],
      "settings": {
        "title": "",
        "heading_size": "h1",
        "image_width": "third",
        "image_ratio": "adapt",
        "columns_desktop": 3,
        "column_alignment": "center",
        "background_style": "none",
        "button_label": "",
        "button_link": "",
        "swipe_on_mobile": false,
        "color_scheme": "scheme-1",
        "columns_mobile": "1",
        "padding_top": 56,
        "padding_bottom": 56
      }
    },
    "aw-nieuwsbrief": {
      "type": "newsletter",
      "blocks": {
        "aw-nl-heading": {
          "type": "heading",
          "settings": {
            "heading": "Ontvang exclusieve aanbiedingen"
          }
        },
        "aw-nl-sub": {
          "type": "subheading",
          "settings": {
            "subheading": "Schrijf u in voor onze nieuwsbrief en ontvang als eerste nieuws over nieuwe collecties en speciale acties."
          }
        },
        "aw-nl-form": {
          "type": "email_form",
          "settings": {}
        }
      },
      "block_order": [
        "aw-nl-heading",
        "aw-nl-sub",
        "aw-nl-form"
      ],
      "settings": {
        "color_scheme": "scheme-5",
        "full_width": true,
        "padding_top": 56,
        "padding_bottom": 56
      }
    }
  },
  "order": [
    "aw-hero",
    "aw-collectie",
    "aw-usp",
    "aw-nieuwsbrief"
  ]
}
